CHANGELOG.md
cli/__init__.py
cli/cli.py
cli/client.py
cli/commands/consumer.py
cli/commands/dev.py
cli/commands/domain.py
cli/commands/human/__init__.py
cli/commands/human/errors.py
cli/commands/human/progress.py
cli/commands/infra.py
cli/commands/jwt.py
cli/commands/options.py
cli/commands/route.py
cli/conf.py
cli/console.py
cli/gateway.py
cli/infra/__init__.py
cli/infra/cockpit.py
cli/infra/container.py
cli/infra/function.py
cli/infra/image.py
cli/infra/manager.py
cli/infra/rdb.py
cli/infra/secrets.py
cli/model.py
scw_gateway-0.6.1.dist-info/WHEEL
scw_gateway-0.6.1.dist-info/METADATA
scw_gateway-0.6.1.dist-info/entry_points.txt
scw_gateway-0.6.1.dist-info/RECORD
