Metadata-Version: 2.1
Name: scw-gateway
Version: 0.6.1
Summary: CLI to deploy and manage a self-hosted Kong gateway on Scaleway Serverless Ecosystem
Home-page: https://github.com/scaleway/serverless-gateway
Keywords: serverless,scaleway,gateway,cloud,caas
Author: Simon Shillaker
Author-email: sshillaker@scaleway.com
Requires-Python: >=3.10,<4.0
Classifier: Development Status :: 3 - Alpha
Classifier: Intended Audience :: Developers
Classifier: Intended Audience :: Information Technology
Classifier: License :: OSI Approved :: MIT License
Classifier: Programming Language :: Python
Classifier: Programming Language :: Python :: 3
Classifier: Programming Language :: Python :: 3.10
Classifier: Programming Language :: Python :: 3.11
Classifier: Programming Language :: Python :: 3.10
Classifier: Programming Language :: Python :: 3.11
Classifier: Topic :: Internet
Classifier: Topic :: Software Development :: Libraries :: Application Frameworks
Requires-Dist: click (>=8.1.3,<9.0.0)
Requires-Dist: loguru (==0.6.0)
Requires-Dist: pyyaml (>=6.0,<7.0)
Requires-Dist: requests (>=2.28.2,<3.0.0)
Requires-Dist: rich (>=13.4.2,<14.0.0)
Requires-Dist: scaleway (>=0.12.0,<0.13.0)
Project-URL: Documentation, https://serverless-gateway.readthedocs.io/en/latest/
Project-URL: Repository, https://github.com/scaleway/serverless-gateway
